aitomic/__init__.py
aitomic/bruker.py
aitomic/nomad_nmr.py
aitomic/py.typed
aitomic/_internal/__init__.py
aitomic/_internal/bruker.py
aitomic/_internal/nomad_nmr.py
aitomic-0.2.1.dist-info/LICENSE
aitomic-0.2.1.dist-info/METADATA
aitomic-0.2.1.dist-info/WHEEL
aitomic-0.2.1.dist-info/top_level.txt
aitomic-0.2.1.dist-info/RECORD
