Metadata-Version: 2.1
Name: aitomic
Version: 0.2.1
Summary: Make AI in chemistry simple!
Maintainer-email: Lukas Turcani <lukasturcani93@gmail.com>
Project-URL: github, https://github.com/aichemy-hub/aitomic
Project-URL: documentation, https://aitomic.readthedocs.io
Requires-Python: >=3.12
License-File: LICENSE
Requires-Dist: nmrglue>=0.11
Requires-Dist: polars>=1.12.0
Requires-Dist: pydantic>=2.9.2
Requires-Dist: requests>=2.32.3
Requires-Dist: types-requests>=2.32.0.20241016
